LICENSE
MANIFEST.in
README.rst
setup.py
pakker/__init__.py
pakker.egg-info/PKG-INFO
pakker.egg-info/SOURCES.txt
pakker.egg-info/dependency_links.txt
pakker.egg-info/requires.txt
pakker.egg-info/top_level.txt
pakker/php/__init__.py
pakker/php/_serialize.py
pakker/php/_unserialize.c
pakker/tests/__init__.py
pakker/tests/test_php.py