Metadata-Version: 1.1
Name: pakker
Version: 0.2
Summary: Library for dealing with language-specific serialization formats.
Home-page: http://buffer.io/+pakker/
Author: Andreas Stührk
Author-email: andy-python@hammerhartes.de
License: BSD
Platform: UNKNOWN
Classifier: License :: OSI Approved :: BSD License
Classifier: Programming Language :: Python
Classifier: Programming Language :: Python :: 3
